{"nm":"Pay","ddd":0,"h":304,"w":304,"meta":{"g":"LottieFiles AE 3.0.2"},"layers":[{"ty":0,"nm":"Finle Sand","sr":1,"st":0,"op":268,"ip":0,"hd":false,"ddd":0,"bm":0,"hasMask":false,"ao":0,"ks":{"a":{"a":0,"k":[540,540,0],"ix":1},"s":{"a":0,"k":[100,100,100],"ix":6},"sk":{"a":0,"k":0},"p":{"a":0,"k":[97,166,0],"ix":2},"r":{"a":0,"k":0,"ix":10},"sa":{"a":0,"k":0},"o":{"a":0,"k":100,"ix":11}},"ef":[],"w":1080,"h":1080,"refId":"comp_0","ind":1},{"ty":4,"nm":"Layer 2 Outlines","sr":1,"st":0,"op":268,"ip":0,"hd":false,"ddd":0,"bm":0,"hasMask":false,"ao":0,"ks":{"a":{"a":0,"k":[58.927,234.625,0],"ix":1},"s":{"a":0,"k":[100,100,100],"ix":6},"sk":{"a":0,"k":0},"p":{"a":1,"k":[{"o":{"x":0.483,"y":0},"i":{"x":0.667,"y":1},"s":[245.927,74.625,0],"t":0,"ti":[11.5,0,0],"to":[-11.5,0,0]},{"o":{"x":0.483,"y":0.483},"i":{"x":0.667,"y":0.667},"s":[176.927,74.625,0],"t":47,"ti":[0,0,0],"to":[0,0,0]},{"o":{"x":0.483,"y":0},"i":{"x":0.667,"y":1},"s":[176.927,74.625,0],"t":172,"ti":[-11.5,0,0],"to":[11.5,0,0]},{"s":[245.927,74.625,0],"t":228}],"ix":2},"r":{"a":1,"k":[{"o":{"x":0.333,"y":0},"i":{"x":0.667,"y":1},"s":[0],"t":47},{"o":{"x":0.333,"y":0},"i":{"x":0.833,"y":1},"s":[20.715],"t":67},{"o":{"x":0.167,"y":0},"i":{"x":0.667,"y":1},"s":[-20.715],"t":105},{"o":{"x":0.333,"y":0},"i":{"x":0.667,"y":1},"s":[20.715],"t":144},{"s":[0],"t":172}],"ix":10},"sa":{"a":0,"k":0},"o":{"a":0,"k":100,"ix":11}},"ef":[],"shapes":[{"ty":"gr","bm":0,"hd":false,"mn":"ADBE Vector Group","nm":"Group 1","ix":1,"cix":2,"np":2,"it":[{"ty":"sh","bm":0,"hd":false,"mn":"ADBE Vector Shape - Group","nm":"Path 1","ix":1,"d":1,"ks":{"a":0,"k":{"c":true,"i":[[0.757,0],[0,0],[0,0.757],[-0.758,0],[0,0],[0,-0.758]],"o":[[0,0],[-0.758,0],[0,-0.758],[0,0],[0.757,0],[0,0.757]],"v":[[7.117,1.37],[-7.117,1.37],[-8.487,0.001],[-7.117,-1.369],[7.117,-1.369],[8.487,0.001]]},"ix":2}},{"ty":"fl","bm":0,"hd":false,"mn":"ADBE Vector Graphic - Fill","nm":"Fill 1","c":{"a":0,"k":[0.4235,0.4235,0.4275,1],"ix":4},"r":1,"o":{"a":0,"k":100,"ix":5}},{"ty":"tr","a":{"a":0,"k":[0,0],"ix":1},"s":{"a":0,"k":[100,100],"ix":3},"sk":{"a":0,"k":0,"ix":4},"p":{"a":0,"k":[88.763,244.203],"ix":2},"r":{"a":0,"k":0,"ix":6},"sa":{"a":0,"k":0,"ix":5},"o":{"a":0,"k":100,"ix":7}}]},{"ty":"gr","bm":0,"hd":false,"mn":"ADBE Vector Group","nm":"Group 2","ix":2,"cix":2,"np":2,"it":[{"ty":"sh","bm":0,"hd":false,"mn":"ADBE Vector Shape - Group","nm":"Path 1","ix":1,"d":1,"ks":{"a":0,"k":{"c":true,"i":[[0.757,0],[0,0],[0,0.757],[-0.758,0],[0,0],[0,-0.758]],"o":[[0,0],[-0.758,0],[0,-0.758],[0,0],[0.757,0],[0,0.757]],"v":[[7.117,1.37],[-7.117,1.37],[-8.487,0.001],[-7.117,-1.369],[7.117,-1.369],[8.487,0.001]]},"ix":2}},{"ty":"fl","bm":0,"hd":false,"mn":"ADBE Vector Graphic - Fill","nm":"Fill 1","c":{"a":0,"k":[0.4235,0.4235,0.4275,1],"ix":4},"r":1,"o":{"a":0,"k":100,"ix":5}},{"ty":"tr","a":{"a":0,"k":[0,0],"ix":1},"s":{"a":0,"k":[100,100],"ix":3},"sk":{"a":0,"k":0,"ix":4},"p":{"a":0,"k":[67.782,244.203],"ix":2},"r":{"a":0,"k":0,"ix":6},"sa":{"a":0,"k":0,"ix":5},"o":{"a":0,"k":100,"ix":7}}]},{"ty":"gr","bm":0,"hd":false,"mn":"ADBE Vector Group","nm":"Group 3","ix":3,"cix":2,"np":2,"it":[{"ty":"sh","bm":0,"hd":false,"mn":"ADBE Vector Shape - Group","nm":"Path 1","ix":1,"d":1,"ks":{"a":0,"k":{"c":true,"i":[[0.757,0],[0,0],[0,0.757],[-0.757,0],[0,0],[0,-0.758]],"o":[[0,0],[-0.757,0],[0,-0.758],[0,0],[0.757,0],[0,0.757]],"v":[[7.117,1.37],[-7.117,1.37],[-8.487,0.001],[-7.117,-1.369],[7.117,-1.369],[8.487,0.001]]},"ix":2}},{"ty":"fl","bm":0,"hd":false,"mn":"ADBE Vector Graphic - Fill","nm":"Fill 1","c":{"a":0,"k":[0.4235,0.4235,0.4275,1],"ix":4},"r":1,"o":{"a":0,"k":100,"ix":5}},{"ty":"tr","a":{"a":0,"k":[0,0],"ix":1},"s":{"a":0,"k":[100,100],"ix":3},"sk":{"a":0,"k":0,"ix":4},"p":{"a":0,"k":[46.801,244.203],"ix":2},"r":{"a":0,"k":0,"ix":6},"sa":{"a":0,"k":0,"ix":5},"o":{"a":0,"k":100,"ix":7}}]},{"ty":"gr","bm":0,"hd":false,"mn":"ADBE Vector Group","nm":"Group 4","ix":4,"cix":2,"np":2,"it":[{"ty":"sh","bm":0,"hd":false,"mn":"ADBE Vector Shape - Group","nm":"Path 1","ix":1,"d":1,"ks":{"a":0,"k":{"c":true,"i":[[0.757,0],[0,0],[0,0.757],[-0.757,0],[0,0],[0,-0.758]],"o":[[0,0],[-0.757,0],[0,-0.758],[0,0],[0.757,0],[0,0.757]],"v":[[7.117,1.37],[-7.117,1.37],[-8.487,0.001],[-7.117,-1.369],[7.117,-1.369],[8.487,0.001]]},"ix":2}},{"ty":"fl","bm":0,"hd":false,"mn":"ADBE Vector Graphic - Fill","nm":"Fill 1","c":{"a":0,"k":[0.4235,0.4235,0.4275,1],"ix":4},"r":1,"o":{"a":0,"k":100,"ix":5}},{"ty":"tr","a":{"a":0,"k":[0,0],"ix":1},"s":{"a":0,"k":[100,100],"ix":3},"sk":{"a":0,"k":0,"ix":4},"p":{"a":0,"k":[25.82,244.203],"ix":2},"r":{"a":0,"k":0,"ix":6},"sa":{"a":0,"k":0,"ix":5},"o":{"a":0,"k":100,"ix":7}}]},{"ty":"gr","bm":0,"hd":false,"mn":"ADBE Vector Group","nm":"Group 5","ix":5,"cix":2,"np":2,"it":[{"ty":"sh","bm":0,"hd":false,"mn":"ADBE Vector Shape - Group","nm":"Path 1","ix":1,"d":1,"ks":{"a":0,"k":{"c":true,"i":[[0.757,0],[0,0],[0,0.757],[-0.758,0],[0,0],[0,-0.758]],"o":[[0,0],[-0.758,0],[0,-0.758],[0,0],[0.757,0],[0,0.757]],"v":[[52.432,1.369],[-52.432,1.369],[-53.802,0],[-52.432,-1.37],[52.432,-1.37],[53.802,0]]},"ix":2}},{"ty":"fl","bm":0,"hd":false,"mn":"ADBE Vector Graphic - Fill","nm":"Fill 1","c":{"a":0,"k":[0.4235,0.4235,0.4275,1],"ix":4},"r":1,"o":{"a":0,"k":100,"ix":5}},{"ty":"tr","a":{"a":0,"k":[0,0],"ix":1},"s":{"a":0,"k":[100,100],"ix":3},"sk":{"a":0,"k":0,"ix":4},"p":{"a":0,"k":[58.294,224.853],"ix":2},"r":{"a":0,"k":0,"ix":6},"sa":{"a":0,"k":0,"ix":5},"o":{"a":0,"k":100,"ix":7}}]},{"ty":"gr","bm":0,"hd":false,"mn":"ADBE Vector Group","nm":"Group 6","ix":6,"cix":2,"np":4,"it":[{"ty":"sh","bm":0,"hd":false,"mn":"ADBE Vector Shape - Group","nm":"Path 1","ix":1,"d":1,"ks":{"a":0,"k":{"c":true,"i":[[0,0],[0,-3.431],[0,0],[-3.432,0],[0,0],[0,3.431],[0,0],[3.432,0]],"o":[[-3.432,0],[0,0],[0,3.431],[0,0],[3.432,0],[0,0],[0,-3.431],[0,0]],"v":[[-45.473,-33.334],[-51.695,-27.113],[-51.695,27.113],[-45.473,33.334],[45.473,33.334],[51.695,27.113],[51.695,-27.113],[45.473,-33.334]]},"ix":2}},{"ty":"sh","bm":0,"hd":false,"mn":"ADBE Vector Shape - Group","nm":"Path 2","ix":2,"d":1,"ks":{"a":0,"k":{"c":true,"i":[[4.941,0],[0,0],[0,4.941],[0,0],[-4.941,0],[0,0],[0,-4.941],[0,0]],"o":[[0,0],[-4.941,0],[0,0],[0,-4.941],[0,0],[4.941,0],[0,0],[0,4.941]],"v":[[45.473,36.072],[-45.473,36.072],[-54.434,27.113],[-54.434,-27.113],[-45.473,-36.072],[45.473,-36.072],[54.434,-27.113],[54.434,27.113]]},"ix":2}},{"ty":"mm","bm":0,"hd":false,"mn":"ADBE Vector Filter - Merge","nm":"Merge Paths 1","mm":1},{"ty":"fl","bm":0,"hd":false,"mn":"ADBE Vector Graphic - Fill","nm":"Fill 1","c":{"a":0,"k":[0.4235,0.4235,0.4275,1],"ix":4},"r":1,"o":{"a":0,"k":100,"ix":5}},{"ty":"tr","a":{"a":0,"k":[0,0],"ix":1},"s":{"a":0,"k":[100,100],"ix":3},"sk":{"a":0,"k":0,"ix":4},"p":{"a":0,"k":[58.927,234.625],"ix":2},"r":{"a":0,"k":0,"ix":6},"sa":{"a":0,"k":0,"ix":5},"o":{"a":0,"k":100,"ix":7}}]},{"ty":"gr","bm":0,"hd":false,"mn":"ADBE Vector Group","nm":"Group 7","ix":7,"cix":2,"np":2,"it":[{"ty":"sh","bm":0,"hd":false,"mn":"ADBE Vector Shape - Group","nm":"Path 1","ix":1,"d":1,"ks":{"a":0,"k":{"c":true,"i":[[4.192,0],[0,0],[0,4.192],[0,0],[-4.192,0],[0,0],[0,-4.193],[0,0]],"o":[[0,0],[-4.192,0],[0,0],[0,-4.193],[0,0],[4.192,0],[0,0],[0,4.192]],"v":[[45.474,34.703],[-45.474,34.703],[-53.065,27.112],[-53.065,-27.112],[-45.474,-34.703],[45.474,-34.703],[53.065,-27.112],[53.065,27.112]]},"ix":2}},{"ty":"fl","bm":0,"hd":false,"mn":"ADBE Vector Graphic - Fill","nm":"Fill 1","c":{"a":0,"k":[1,1,1,1],"ix":4},"r":1,"o":{"a":0,"k":100,"ix":5}},{"ty":"tr","a":{"a":0,"k":[0,0],"ix":1},"s":{"a":0,"k":[100,100],"ix":3},"sk":{"a":0,"k":0,"ix":4},"p":{"a":0,"k":[58.927,234.625],"ix":2},"r":{"a":0,"k":0,"ix":6},"sa":{"a":0,"k":0,"ix":5},"o":{"a":0,"k":100,"ix":7}}]}],"ind":2},{"ty":4,"nm":"Layer 1 Outlines","sr":1,"st":0,"op":268,"ip":0,"hd":false,"ddd":0,"bm":0,"hasMask":false,"ao":0,"ks":{"a":{"a":0,"k":[129.923,154.37,0],"ix":1},"s":{"a":0,"k":[100,100,100],"ix":6},"sk":{"a":0,"k":0},"p":{"a":0,"k":[41.923,152.37,0],"ix":2},"r":{"a":0,"k":0,"ix":10},"sa":{"a":0,"k":0},"o":{"a":0,"k":100,"ix":11}},"ef":[],"shapes":[{"ty":"gr","bm":0,"hd":false,"mn":"ADBE Vector Group","nm":"Group 1","ix":1,"cix":2,"np":5,"it":[{"ty":"sh","bm":0,"hd":false,"mn":"ADBE Vector Shape - Group","nm":"Path 1","ix":1,"d":1,"ks":{"a":0,"k":{"c":true,"i":[[0,1.206],[0.566,0.745],[1.382,0.532],[0,0],[-0.709,0.763]],"o":[[0,-1.063],[-0.565,-0.745],[0,0],[1.347,-0.248],[0.709,-0.762]],"v":[[6.488,8.374],[5.635,5.663],[2.712,3.749],[2.34,12.842],[5.423,11.326]]},"ix":2}},{"ty":"sh","bm":0,"hd":false,"mn":"ADBE Vector Shape - Group","nm":"Path 2","ix":2,"d":1,"ks":{"a":0,"k":{"c":true,"i":[[0,-1.099],[-0.551,-0.727],[-1.455,-0.459],[0,0],[0.692,-0.745]],"o":[[0,0.921],[0.549,0.726],[0,0],[-1.383,0.248],[-0.691,0.744]],"v":[[-6.327,-9.544],[-5.504,-7.072],[-2.497,-5.292],[-2.18,-13.798],[-5.29,-12.309]]},"ix":2}},{"ty":"sh","bm":0,"hd":false,"mn":"ADBE Vector Shape - Group","nm":"Path 3","ix":3,"d":1,"ks":{"a":0,"k":{"c":true,"i":[[0,-3.296],[2.357,-2.18],[3.794,-0.355],[0,0],[0,0],[0,0],[1.861,1.453],[0.673,1.88],[0,0],[0,0],[-0.764,-0.745],[-1.205,-0.355],[0,0],[0,0],[1.952,1.862],[0,3.191],[-2.321,2.11],[-3.829,0.284],[0,0],[0,0],[0,0],[-1.7,-1.329],[-0.461,-1.985],[0,0],[0,0],[0.46,0.727],[0.886,0.39],[0,0],[0,0],[-2.091,-1.915]],"o":[[0,3.473],[-2.357,2.18],[0,0],[0,0],[0,0],[-3.085,-0.461],[-1.86,-1.454],[0,0],[0,0],[0.353,1.099],[0.761,0.744],[0,0],[0,0],[-3.652,-0.745],[-1.948,-1.861],[0,-3.543],[2.321,-2.108],[0,0],[0,0],[0,0],[2.657,0.426],[1.703,1.329],[0,0],[0,0],[-0.248,-0.886],[-0.461,-0.725],[0,0],[0,0],[3.616,0.78],[2.094,1.914]],"v":[[14.781,7.896],[11.245,16.378],[2.02,20.18],[1.755,27.092],[-3.827,27.092],[-3.562,20.073],[-10.98,17.202],[-14.782,12.202],[-14.782,8.215],[-7.87,8.215],[-6.195,10.98],[-3.245,12.629],[-2.818,2.525],[-3.297,2.42],[-11.7,-1.49],[-14.622,-9.066],[-11.141,-17.548],[-1.915,-21.137],[-1.65,-27.092],[3.936,-27.092],[3.671,-20.87],[10.208,-18.238],[13.451,-13.268],[13.451,-9.225],[6.488,-9.225],[5.423,-11.645],[3.402,-13.32],[3.031,-3.962],[3.084,-3.962],[11.643,0.079]]},"ix":2}},{"ty":"mm","bm":0,"hd":false,"mn":"ADBE Vector Filter - Merge","nm":"Merge Paths 1","mm":1},{"ty":"fl","bm":0,"hd":false,"mn":"ADBE Vector Graphic - Fill","nm":"Fill 1","c":{"a":0,"k":[1,1,1,1],"ix":4},"r":1,"o":{"a":0,"k":100,"ix":5}},{"ty":"tr","a":{"a":0,"k":[0,0],"ix":1},"s":{"a":0,"k":[100,100],"ix":3},"sk":{"a":0,"k":0,"ix":4},"p":{"a":0,"k":[174.266,157.784],"ix":2},"r":{"a":0,"k":0,"ix":6},"sa":{"a":0,"k":0,"ix":5},"o":{"a":0,"k":100,"ix":7}}]},{"ty":"gr","bm":0,"hd":false,"mn":"ADBE Vector Group","nm":"Group 2","ix":2,"cix":2,"np":4,"it":[{"ty":"sh","bm":0,"hd":false,"mn":"ADBE Vector Shape - Group","nm":"Path 1","ix":1,"d":1,"ks":{"a":0,"k":{"c":true,"i":[[17.257,0],[0,-17.257],[-17.257,0],[0,17.258]],"o":[[-17.257,0],[0,17.258],[17.257,0],[0,-17.257]],"v":[[0,-31.296],[-31.296,0],[0,31.297],[31.296,0]]},"ix":2}},{"ty":"sh","bm":0,"hd":false,"mn":"ADBE Vector Shape - Group","nm":"Path 2","ix":2,"d":1,"ks":{"a":0,"k":{"c":true,"i":[[18.012,0],[0,18.012],[-18.011,0],[0,-18.011]],"o":[[-18.011,0],[0,-18.011],[18.012,0],[0,18.012]],"v":[[0,32.666],[-32.666,0],[0,-32.666],[32.666,0]]},"ix":2}},{"ty":"mm","bm":0,"hd":false,"mn":"ADBE Vector Filter - Merge","nm":"Merge Paths 1","mm":1},{"ty":"fl","bm":0,"hd":false,"mn":"ADBE Vector Graphic - Fill","nm":"Fill 1","c":{"a":0,"k":[1,1,1,1],"ix":4},"r":1,"o":{"a":0,"k":100,"ix":5}},{"ty":"tr","a":{"a":0,"k":[0,0],"ix":1},"s":{"a":0,"k":[100,100],"ix":3},"sk":{"a":0,"k":0,"ix":4},"p":{"a":0,"k":[174.266,157.784],"ix":2},"r":{"a":0,"k":0,"ix":6},"sa":{"a":0,"k":0,"ix":5},"o":{"a":0,"k":100,"ix":7}}]},{"ty":"gr","bm":0,"hd":false,"mn":"ADBE Vector Group","nm":"Group 3","ix":3,"cix":2,"np":4,"it":[{"ty":"sh","bm":0,"hd":false,"mn":"ADBE Vector Shape - Group","nm":"Path 1","ix":1,"d":1,"ks":{"a":0,"k":{"c":true,"i":[[21.045,0],[0,-21.046],[-21.045,0],[0,21.047]],"o":[[-21.045,0],[0,21.047],[21.045,0],[0,-21.046]],"v":[[0,-38.168],[-38.168,0],[0,38.169],[38.168,0]]},"ix":2}},{"ty":"sh","bm":0,"hd":false,"mn":"ADBE Vector Shape - Group","nm":"Path 2","ix":2,"d":1,"ks":{"a":0,"k":{"c":true,"i":[[22.557,0],[0,22.557],[-22.556,0],[0,-22.557]],"o":[[-22.556,0],[0,-22.557],[22.557,0],[0,22.557]],"v":[[0,40.908],[-40.908,0],[0,-40.907],[40.908,0]]},"ix":2}},{"ty":"mm","bm":0,"hd":false,"mn":"ADBE Vector Filter - Merge","nm":"Merge Paths 1","mm":1},{"ty":"fl","bm":0,"hd":false,"mn":"ADBE Vector Graphic - Fill","nm":"Fill 1","c":{"a":0,"k":[0.4235,0.4235,0.4275,1],"ix":4},"r":1,"o":{"a":0,"k":100,"ix":5}},{"ty":"tr","a":{"a":0,"k":[0,0],"ix":1},"s":{"a":0,"k":[100,100],"ix":3},"sk":{"a":0,"k":0,"ix":4},"p":{"a":0,"k":[174.266,157.784],"ix":2},"r":{"a":0,"k":0,"ix":6},"sa":{"a":0,"k":0,"ix":5},"o":{"a":0,"k":100,"ix":7}}]},{"ty":"gr","bm":0,"hd":false,"mn":"ADBE Vector Group","nm":"Group 4","ix":4,"cix":2,"np":2,"it":[{"ty":"sh","bm":0,"hd":false,"mn":"ADBE Vector Shape - Group","nm":"Path 1","ix":1,"d":1,"ks":{"a":0,"k":{"c":true,"i":[[-21.343,0],[-0.775,-21.155],[0,0.493],[21.837,0],[0,-21.836],[-0.018,-0.489]],"o":[[21.344,0],[0.017,-0.489],[0,-21.836],[-21.836,0],[0,0.493],[0.775,-21.155]],"v":[[-0.001,-17.579],[39.464,20.499],[39.538,19.038],[-0.001,-20.499],[-39.539,19.038],[-39.465,20.499]]},"ix":2}},{"ty":"fl","bm":0,"hd":false,"mn":"ADBE Vector Graphic - Fill","nm":"Fill 1","c":{"a":0,"k":[1,1,1,1],"ix":4},"r":1,"o":{"a":0,"k":100,"ix":5}},{"ty":"tr","a":{"a":0,"k":[0,0],"ix":1},"s":{"a":0,"k":[100,100],"ix":3},"sk":{"a":0,"k":0,"ix":4},"p":{"a":0,"k":[174.267,138.745],"ix":2},"r":{"a":0,"k":0,"ix":6},"sa":{"a":0,"k":0,"ix":5},"o":{"a":0,"k":100,"ix":7}}]},{"ty":"gr","bm":0,"hd":false,"mn":"ADBE Vector Group","nm":"Group 5","ix":5,"cix":2,"np":2,"it":[{"ty":"sh","bm":0,"hd":false,"mn":"ADBE Vector Shape - Group","nm":"Path 1","ix":1,"d":1,"ks":{"a":0,"k":{"c":true,"i":[[0,-21.836],[21.837,0],[0,21.837],[-21.836,0]],"o":[[0,21.837],[-21.836,0],[0,-21.836],[21.837,0]],"v":[[39.539,0],[0,39.538],[-39.538,0],[0,-39.538]]},"ix":2}},{"ty":"fl","bm":0,"hd":false,"mn":"ADBE Vector Graphic - Fill","nm":"Fill 1","c":{"a":0,"k":[0.5,0.5,0.5,1],"ix":4},"r":1,"o":{"a":0,"k":100,"ix":5}},{"ty":"tr","a":{"a":0,"k":[0,0],"ix":1},"s":{"a":0,"k":[100,100],"ix":3},"sk":{"a":0,"k":0,"ix":4},"p":{"a":0,"k":[174.266,157.784],"ix":2},"r":{"a":0,"k":0,"ix":6},"sa":{"a":0,"k":0,"ix":5},"o":{"a":0,"k":100,"ix":7}}]},{"ty":"gr","bm":0,"hd":false,"mn":"ADBE Vector Group","nm":"Group 6","ix":6,"cix":2,"np":2,"it":[{"ty":"sh","bm":0,"hd":false,"mn":"ADBE Vector Shape - Group","nm":"Path 1","ix":1,"d":1,"ks":{"a":0,"k":{"c":true,"i":[[0.757,0],[0,0],[0,0.757],[-0.756,0],[0,0],[0,-0.758]],"o":[[0,0],[-0.756,0],[0,-0.758],[0,0],[0.757,0],[0,0.757]],"v":[[9.978,1.37],[-9.979,1.37],[-11.348,0],[-9.979,-1.37],[9.978,-1.37],[11.348,0]]},"ix":2}},{"ty":"fl","bm":0,"hd":false,"mn":"ADBE Vector Graphic - Fill","nm":"Fill 1","c":{"a":0,"k":[0.4235,0.4235,0.4275,1],"ix":4},"r":1,"o":{"a":0,"k":100,"ix":5}},{"ty":"tr","a":{"a":0,"k":[0,0],"ix":1},"s":{"a":0,"k":[100,100],"ix":3},"sk":{"a":0,"k":0,"ix":4},"p":{"a":0,"k":[172.126,287.239],"ix":2},"r":{"a":0,"k":0,"ix":6},"sa":{"a":0,"k":0,"ix":5},"o":{"a":0,"k":100,"ix":7}}]},{"ty":"gr","bm":0,"hd":false,"mn":"ADBE Vector Group","nm":"Group 7","ix":7,"cix":2,"np":2,"it":[{"ty":"sh","bm":0,"hd":false,"mn":"ADBE Vector Shape - Group","nm":"Path 1","ix":1,"d":1,"ks":{"a":0,"k":{"c":true,"i":[[0.351,0],[0.267,0.267],[-0.535,0.535],[0,0],[-0.536,-0.535],[0.534,-0.535],[0,0]],"o":[[-0.35,0],[-0.535,-0.536],[0,0],[0.535,-0.535],[0.534,0.535],[0,0],[-0.268,0.267]],"v":[[-3.463,4.9],[-4.431,4.499],[-4.431,2.562],[2.495,-4.365],[4.432,-4.365],[4.432,-2.428],[-2.494,4.499]]},"ix":2}},{"ty":"fl","bm":0,"hd":false,"mn":"ADBE Vector Graphic - Fill","nm":"Fill 1","c":{"a":0,"k":[0.4235,0.4235,0.4275,1],"ix":4},"r":1,"o":{"a":0,"k":100,"ix":5}},{"ty":"tr","a":{"a":0,"k":[0,0],"ix":1},"s":{"a":0,"k":[100,100],"ix":3},"sk":{"a":0,"k":0,"ix":4},"p":{"a":0,"k":[187.458,109.517],"ix":2},"r":{"a":0,"k":0,"ix":6},"sa":{"a":0,"k":0,"ix":5},"o":{"a":0,"k":100,"ix":7}}]},{"ty":"gr","bm":0,"hd":false,"mn":"ADBE Vector Group","nm":"Group 8","ix":8,"cix":2,"np":2,"it":[{"ty":"sh","bm":0,"hd":false,"mn":"ADBE Vector Shape - Group","nm":"Path 1","ix":1,"d":1,"ks":{"a":0,"k":{"c":true,"i":[[0.351,0],[0.267,0.267],[0,0],[-0.535,0.535],[-0.534,-0.535],[0,0],[0.535,-0.536]],"o":[[-0.35,0],[0,0],[-0.535,-0.535],[0.535,-0.535],[0,0],[0.535,0.535],[-0.268,0.267]],"v":[[3.462,4.9],[2.494,4.499],[-4.432,-2.428],[-4.432,-4.365],[-2.496,-4.365],[4.431,2.562],[4.431,4.499]]},"ix":2}},{"ty":"fl","bm":0,"hd":false,"mn":"ADBE Vector Graphic - Fill","nm":"Fill 1","c":{"a":0,"k":[0.4235,0.4235,0.4275,1],"ix":4},"r":1,"o":{"a":0,"k":100,"ix":5}},{"ty":"tr","a":{"a":0,"k":[0,0],"ix":1},"s":{"a":0,"k":[100,100],"ix":3},"sk":{"a":0,"k":0,"ix":4},"p":{"a":0,"k":[163.749,109.517],"ix":2},"r":{"a":0,"k":0,"ix":6},"sa":{"a":0,"k":0,"ix":5},"o":{"a":0,"k":100,"ix":7}}]},{"ty":"gr","bm":0,"hd":false,"mn":"ADBE Vector Group","nm":"Group 9","ix":9,"cix":2,"np":2,"it":[{"ty":"sh","bm":0,"hd":false,"mn":"ADBE Vector Shape - Group","nm":"Path 1","ix":1,"d":1,"ks":{"a":0,"k":{"c":true,"i":[[0.757,0],[0,0.758],[0,0],[-0.757,0],[0,-0.758],[0,0]],"o":[[-0.757,0],[0,0],[0,-0.758],[0.757,0],[0,0],[0,0.758]],"v":[[0,5.921],[-1.37,4.551],[-1.37,-4.551],[0,-5.921],[1.37,-4.551],[1.37,4.551]]},"ix":2}},{"ty":"fl","bm":0,"hd":false,"mn":"ADBE Vector Graphic - Fill","nm":"Fill 1","c":{"a":0,"k":[0.4235,0.4235,0.4275,1],"ix":4},"r":1,"o":{"a":0,"k":100,"ix":5}},{"ty":"tr","a":{"a":0,"k":[0,0],"ix":1},"s":{"a":0,"k":[100,100],"ix":3},"sk":{"a":0,"k":0,"ix":4},"p":{"a":0,"k":[175.603,106.121],"ix":2},"r":{"a":0,"k":0,"ix":6},"sa":{"a":0,"k":0,"ix":5},"o":{"a":0,"k":100,"ix":7}}]},{"ty":"gr","bm":0,"hd":false,"mn":"ADBE Vector Group","nm":"Group 10","ix":10,"cix":2,"np":2,"it":[{"ty":"sh","bm":0,"hd":false,"mn":"ADBE Vector Shape - Group","nm":"Path 1","ix":1,"d":1,"ks":{"a":0,"k":{"c":true,"i":[[0.757,0],[0,0],[0,0.757],[-0.758,0],[0,0],[0,-0.757]],"o":[[0,0],[-0.758,0],[0,-0.757],[0,0],[0.757,0],[0,0.757]],"v":[[17.763,1.369],[-17.762,1.369],[-19.132,-0.001],[-17.762,-1.369],[17.763,-1.369],[19.133,-0.001]]},"ix":2}},{"ty":"fl","bm":0,"hd":false,"mn":"ADBE Vector Graphic - Fill","nm":"Fill 1","c":{"a":0,"k":[0.4235,0.4235,0.4275,1],"ix":4},"r":1,"o":{"a":0,"k":100,"ix":5}},{"ty":"tr","a":{"a":0,"k":[0,0],"ix":1},"s":{"a":0,"k":[100,100],"ix":3},"sk":{"a":0,"k":0,"ix":4},"p":{"a":0,"k":[172.075,32.408],"ix":2},"r":{"a":0,"k":0,"ix":6},"sa":{"a":0,"k":0,"ix":5},"o":{"a":0,"k":100,"ix":7}}]},{"ty":"gr","bm":0,"hd":false,"mn":"ADBE Vector Group","nm":"Group 11","ix":11,"cix":2,"np":2,"it":[{"ty":"sh","bm":0,"hd":false,"mn":"ADBE Vector Shape - Group","nm":"Path 1","ix":1,"d":1,"ks":{"a":0,"k":{"c":true,"i":[[0,-2.5],[2.5,0],[0,2.5],[-2.5,0]],"o":[[0,2.5],[-2.5,0],[0,-2.5],[2.5,0]],"v":[[4.527,0],[0,4.527],[-4.527,0],[0,-4.527]]},"ix":2}},{"ty":"fl","bm":0,"hd":false,"mn":"ADBE Vector Graphic - Fill","nm":"Fill 1","c":{"a":0,"k":[0.4235,0.4235,0.4275,1],"ix":4},"r":1,"o":{"a":0,"k":100,"ix":5}},{"ty":"tr","a":{"a":0,"k":[0,0],"ix":1},"s":{"a":0,"k":[100,100],"ix":3},"sk":{"a":0,"k":0,"ix":4},"p":{"a":0,"k":[172.075,21.224],"ix":2},"r":{"a":0,"k":0,"ix":6},"sa":{"a":0,"k":0,"ix":5},"o":{"a":0,"k":100,"ix":7}}]},{"ty":"gr","bm":0,"hd":false,"mn":"ADBE Vector Group","nm":"Group 12","ix":12,"cix":2,"np":2,"it":[{"ty":"sh","bm":0,"hd":false,"mn":"ADBE Vector Shape - Group","nm":"Path 1","ix":1,"d":1,"ks":{"a":0,"k":{"c":true,"i":[[20.392,0],[0,0],[0,20.392],[0,0],[-20.393,0],[0,0],[0,-0.758],[0.757,0],[0,0],[0,-18.883],[0,0],[-18.881,0],[0,0],[0,18.882],[0,0],[18.881,0],[0,0],[0,0.757],[-0.758,0],[0,0],[0,-20.393],[0,0]],"o":[[0,0],[-20.393,0],[0,0],[0,-20.393],[0,0],[0.757,0],[0,0.757],[0,0],[-18.881,0],[0,0],[0,18.882],[0,0],[18.881,0],[0,0],[0,-18.883],[0,0],[-0.758,0],[0,-0.758],[0,0],[20.392,0],[0,0],[0,20.392]],"v":[[44.313,149.742],[-44.313,149.742],[-81.297,112.759],[-81.297,-112.758],[-44.313,-149.742],[18.79,-149.742],[20.159,-148.372],[18.79,-147.003],[-44.313,-147.003],[-78.558,-112.758],[-78.558,112.759],[-44.313,147.003],[44.313,147.003],[78.557,112.759],[78.557,-112.758],[44.313,-147.003],[31.117,-147.003],[29.747,-148.372],[31.117,-149.742],[44.313,-149.742],[81.296,-112.758],[81.296,112.759]]},"ix":2}},{"ty":"fl","bm":0,"hd":false,"mn":"ADBE Vector Graphic - Fill","nm":"Fill 1","c":{"a":0,"k":[0.4235,0.4235,0.4275,1],"ix":4},"r":1,"o":{"a":0,"k":100,"ix":5}},{"ty":"tr","a":{"a":0,"k":[0,0],"ix":1},"s":{"a":0,"k":[100,100],"ix":3},"sk":{"a":0,"k":0,"ix":4},"p":{"a":0,"k":[172.075,154.039],"ix":2},"r":{"a":0,"k":0,"ix":6},"sa":{"a":0,"k":0,"ix":5},"o":{"a":0,"k":100,"ix":7}}]},{"ty":"gr","bm":0,"hd":false,"mn":"ADBE Vector Group","nm":"Group 13","ix":13,"cix":2,"np":4,"it":[{"ty":"sh","bm":0,"hd":false,"mn":"ADBE Vector Shape - Group","nm":"Path 1","ix":1,"d":1,"ks":{"a":0,"k":{"c":true,"i":[[0,0],[0,-2.373],[0,0],[-2.373,0],[0,0],[0,2.372],[0,0],[2.372,0]],"o":[[-2.373,0],[0,0],[0,2.372],[0,0],[2.372,0],[0,0],[0,-2.373],[0,0]],"v":[[-62.38,-113.764],[-66.685,-109.461],[-66.685,109.461],[-62.38,113.764],[62.382,113.764],[66.686,109.461],[66.686,-109.461],[62.382,-113.764]]},"ix":2}},{"ty":"sh","bm":0,"hd":false,"mn":"ADBE Vector Shape - Group","nm":"Path 2","ix":2,"d":1,"ks":{"a":0,"k":{"c":true,"i":[[3.884,0],[0,0],[0,3.882],[0,0],[-3.885,0],[0,0],[0,-3.883],[0,0]],"o":[[0,0],[-3.885,0],[0,0],[0,-3.883],[0,0],[3.884,0],[0,0],[0,3.882]],"v":[[62.382,116.503],[-62.38,116.503],[-69.424,109.461],[-69.424,-109.461],[-62.38,-116.503],[62.382,-116.503],[69.425,-109.461],[69.425,109.461]]},"ix":2}},{"ty":"mm","bm":0,"hd":false,"mn":"ADBE Vector Filter - Merge","nm":"Merge Paths 1","mm":1},{"ty":"fl","bm":0,"hd":false,"mn":"ADBE Vector Graphic - Fill","nm":"Fill 1","c":{"a":0,"k":[0.4235,0.4235,0.4275,1],"ix":4},"r":1,"o":{"a":0,"k":100,"ix":5}},{"ty":"tr","a":{"a":0,"k":[0,0],"ix":1},"s":{"a":0,"k":[100,100],"ix":3},"sk":{"a":0,"k":0,"ix":4},"p":{"a":0,"k":[172.075,160.349],"ix":2},"r":{"a":0,"k":0,"ix":6},"sa":{"a":0,"k":0,"ix":5},"o":{"a":0,"k":100,"ix":7}}]},{"ty":"gr","bm":0,"hd":false,"mn":"ADBE Vector Group","nm":"Group 14","ix":14,"cix":2,"np":2,"it":[{"ty":"sh","bm":0,"hd":false,"mn":"ADBE Vector Shape - Group","nm":"Path 1","ix":1,"d":1,"ks":{"a":0,"k":{"c":true,"i":[[0,-3.133],[0,0],[-3.133,0],[0,0],[0,3.133],[0,0],[3.133,0],[0,0]],"o":[[0,0],[0,3.133],[0,0],[3.133,0],[0,0],[0,-3.133],[0,0],[-3.133,0]],"v":[[-68.055,-109.461],[-68.055,109.461],[-62.382,115.133],[62.382,115.133],[68.055,109.461],[68.055,-109.461],[62.382,-115.133],[-62.382,-115.133]]},"ix":2}},{"ty":"fl","bm":0,"hd":false,"mn":"ADBE Vector Graphic - Fill","nm":"Fill 1","c":{"a":0,"k":[0.96,0.96,0.96,1],"ix":4},"r":1,"o":{"a":0,"k":100,"ix":5}},{"ty":"tr","a":{"a":0,"k":[0,0],"ix":1},"s":{"a":0,"k":[100,100],"ix":3},"sk":{"a":0,"k":0,"ix":4},"p":{"a":0,"k":[172.075,160.349],"ix":2},"r":{"a":0,"k":0,"ix":6},"sa":{"a":0,"k":0,"ix":5},"o":{"a":0,"k":100,"ix":7}}]},{"ty":"gr","bm":0,"hd":false,"mn":"ADBE Vector Group","nm":"Group 15","ix":15,"cix":2,"np":2,"it":[{"ty":"sh","bm":0,"hd":false,"mn":"ADBE Vector Shape - Group","nm":"Path 1","ix":1,"d":1,"ks":{"a":0,"k":{"c":true,"i":[[0,19.668],[0,0],[-19.669,0],[0,0],[0,-19.668],[0,0],[19.668,0],[0,0]],"o":[[0,0],[0,-19.668],[0,0],[19.668,0],[0,0],[0,19.668],[0,0],[-19.669,0]],"v":[[-79.926,112.76],[-79.926,-112.76],[-44.313,-148.372],[44.313,-148.372],[79.926,-112.76],[79.926,112.76],[44.313,148.372],[-44.313,148.372]]},"ix":2}},{"ty":"fl","bm":0,"hd":false,"mn":"ADBE Vector Graphic - Fill","nm":"Fill 1","c":{"a":0,"k":[0.76,0.76,0.76,1],"ix":4},"r":1,"o":{"a":0,"k":100,"ix":5}},{"ty":"tr","a":{"a":0,"k":[0,0],"ix":1},"s":{"a":0,"k":[100,100],"ix":3},"sk":{"a":0,"k":0,"ix":4},"p":{"a":0,"k":[172.075,154.039],"ix":2},"r":{"a":0,"k":0,"ix":6},"sa":{"a":0,"k":0,"ix":5},"o":{"a":0,"k":100,"ix":7}}]}],"ind":3}],"v":"4.8.0","fr":120,"op":268,"ip":0,"assets":[{"nm":"","id":"comp_0","layers":[{"ty":4,"nm":"Line H","sr":1,"st":0,"op":268,"ip":0,"hd":false,"ddd":0,"bm":0,"hasMask":false,"ao":0,"ks":{"a":{"a":0,"k":[0,0,0],"ix":1},"s":{"a":0,"k":[100,100,100],"ix":6},"sk":{"a":0,"k":0},"p":{"a":0,"k":[-0.25,0,0],"ix":2},"r":{"a":0,"k":0,"ix":10},"sa":{"a":0,"k":0},"o":{"a":0,"k":100,"ix":11}},"ef":[],"shapes":[{"ty":"gr","bm":0,"hd":false,"mn":"ADBE Vector Group","nm":"Group 1","ix":1,"cix":2,"np":2,"it":[{"ty":"sh","bm":0,"hd":false,"mn":"ADBE Vector Shape - Group","nm":"Path 1","ix":1,"d":1,"ks":{"a":0,"k":{"c":true,"i":[[0,0],[-3.484,1.785],[-6.21,11.49],[3.299,8.571],[0,0],[1.516,0],[0,0],[0.604,-1.05],[0,0],[-10.162,-18.801],[-10.208,-5.231],[0,0],[3.485,-1.786],[6.21,-11.489],[-3.299,-8.569],[0,0],[-1.516,0],[0,0],[-0.605,1.048],[0,0],[10.162,18.801],[10.206,5.23]],"o":[[0,0],[10.206,-5.231],[10.162,-18.801],[0,0],[-0.605,-1.051],[0,0],[-1.516,0],[0,0],[-3.299,8.571],[6.21,11.49],[3.485,1.785],[0,0],[-10.206,5.231],[-10.162,18.801],[0,0],[0.604,1.048],[0,0],[1.516,0],[0,0],[3.299,-8.569],[-6.21,-11.489],[-3.484,-1.786]],"v":[[2.708,0.001],[6.37,-4.879],[43.068,-32.046],[45.445,-77.383],[44.167,-80.702],[40.312,-82.611],[-40.312,-82.611],[-44.167,-80.702],[-45.445,-77.383],[-43.068,-32.046],[-6.37,-4.879],[-2.708,0.001],[-6.37,4.881],[-43.068,32.046],[-45.445,77.383],[-44.167,80.704],[-40.312,82.611],[40.312,82.611],[44.167,80.704],[45.445,77.383],[43.068,32.046],[6.37,4.881]]},"ix":2}},{"ty":"st","bm":0,"hd":false,"mn":"ADBE Vector Graphic - Stroke","nm":"Stroke 1","lc":1,"lj":1,"ml":10,"o":{"a":0,"k":100,"ix":4},"w":{"a":0,"k":3,"ix":5},"c":{"a":0,"k":[0.4235,0.4235,0.4275,1],"ix":3}},{"ty":"tr","a":{"a":0,"k":[0,0],"ix":1},"s":{"a":0,"k":[100,100],"ix":3},"sk":{"a":0,"k":0,"ix":4},"p":{"a":0,"k":[51.528,84.672],"ix":2},"r":{"a":0,"k":0,"ix":6},"sa":{"a":0,"k":0,"ix":5},"o":{"a":0,"k":100,"ix":7}}]}],"ind":1,"parent":5},{"ty":4,"nm":"Footer Header","sr":1,"st":0,"op":268,"ip":0,"hd":false,"ddd":0,"bm":0,"hasMask":false,"ao":0,"ks":{"a":{"a":0,"k":[0,0,0],"ix":1},"s":{"a":0,"k":[100,100,100],"ix":6},"sk":{"a":0,"k":0},"p":{"a":0,"k":[-0.25,0,0],"ix":2},"r":{"a":0,"k":0,"ix":10},"sa":{"a":0,"k":0},"o":{"a":0,"k":100,"ix":11}},"ef":[],"shapes":[{"ty":"gr","bm":0,"hd":false,"mn":"ADBE Vector Group","nm":"Group 2","ix":1,"cix":2,"np":2,"it":[{"ty":"sh","bm":0,"hd":false,"mn":"ADBE Vector Shape - Group","nm":"Path 1","ix":1,"d":1,"ks":{"a":0,"k":{"c":true,"i":[[0,0],[0.771,-2.01],[0,0],[1.514,0],[0,0],[0.607,1.046],[0,0],[0.7,2.942]],"o":[[-0.701,2.942],[0,0],[-0.606,1.046],[0,0],[-1.516,0],[0,0],[-0.772,-2.01],[0,0]],"v":[[47.761,-6.359],[45.446,1.129],[44.167,4.454],[40.315,6.36],[-40.315,6.36],[-44.168,4.454],[-45.446,1.129],[-47.761,-6.359]]},"ix":2}},{"ty":"fl","bm":0,"hd":false,"mn":"ADBE Vector Graphic - Fill","nm":"Fill 1","c":{"a":0,"k":[0.5,0.5,0.5,1],"ix":4},"r":1,"o":{"a":0,"k":100,"ix":5}},{"ty":"tr","a":{"a":0,"k":[0,0],"ix":1},"s":{"a":0,"k":[100,100],"ix":3},"sk":{"a":0,"k":0,"ix":4},"p":{"a":0,"k":[51.527,160.924],"ix":2},"r":{"a":0,"k":0,"ix":6},"sa":{"a":0,"k":0,"ix":5},"o":{"a":0,"k":100,"ix":7}}]},{"ty":"gr","bm":0,"hd":false,"mn":"ADBE Vector Group","nm":"Group 3","ix":2,"cix":2,"np":2,"it":[{"ty":"sh","bm":0,"hd":false,"mn":"ADBE Vector Shape - Group","nm":"Path 1","ix":1,"d":1,"ks":{"a":0,"k":{"c":true,"i":[[0.701,-2.942],[0,0],[0.772,2.011],[0,0],[1.515,0],[0,0],[0.608,-1.047],[0,0]],"o":[[0,0],[-0.701,-2.942],[0,0],[-0.607,-1.047],[0,0],[-1.515,0],[0,0],[-0.773,2.011]],"v":[[-47.761,6.36],[47.761,6.36],[45.446,-1.129],[44.168,-4.452],[40.315,-6.36],[-40.315,-6.36],[-44.168,-4.452],[-45.445,-1.129]]},"ix":2}},{"ty":"fl","bm":0,"hd":false,"mn":"ADBE Vector Graphic - Fill","nm":"Fill 1","c":{"a":0,"k":[0.5,0.5,0.5,1],"ix":4},"r":1,"o":{"a":0,"k":100,"ix":5}},{"ty":"tr","a":{"a":0,"k":[0,0],"ix":1},"s":{"a":0,"k":[100,100],"ix":3},"sk":{"a":0,"k":0,"ix":4},"p":{"a":0,"k":[51.527,8.421],"ix":2},"r":{"a":0,"k":0,"ix":6},"sa":{"a":0,"k":0,"ix":5},"o":{"a":0,"k":100,"ix":7}}]}],"ind":2,"parent":5},{"ty":4,"nm":"Shape H 2","sr":1,"st":0,"op":268,"ip":0,"hd":false,"ddd":0,"bm":0,"hasMask":false,"td":1,"ao":0,"ks":{"a":{"a":0,"k":[51.389,84.834,0],"ix":1},"s":{"a":0,"k":[100,100,100],"ix":6},"sk":{"a":0,"k":0},"p":{"a":0,"k":[51.389,84.834,0],"ix":2},"r":{"a":0,"k":0,"ix":10},"sa":{"a":0,"k":0},"o":{"a":0,"k":100,"ix":11}},"ef":[],"shapes":[{"ty":"gr","bm":0,"hd":false,"mn":"ADBE Vector Group","nm":"Group 4","ix":1,"cix":2,"np":4,"it":[{"ty":"sh","bm":0,"hd":false,"mn":"ADBE Vector Shape - Group","nm":"Path 1","ix":1,"d":1,"ks":{"a":0,"k":{"c":true,"i":[[0,0],[-3.484,1.785],[-6.21,11.49],[3.299,8.571],[0,0],[1.516,0],[0,0],[0.604,-1.05],[0,0],[-10.162,-18.801],[-10.208,-5.231],[0,0],[3.485,-1.786],[6.21,-11.489],[-3.299,-8.569],[0,0],[-1.516,0],[0,0],[-0.605,1.048],[0,0],[10.162,18.801],[10.206,5.23]],"o":[[0,0],[10.206,-5.231],[10.162,-18.801],[0,0],[-0.605,-1.051],[0,0],[-1.516,0],[0,0],[-3.299,8.571],[6.21,11.49],[3.485,1.785],[0,0],[-10.206,5.231],[-10.162,18.801],[0,0],[0.604,1.048],[0,0],[1.516,0],[0,0],[3.299,-8.569],[-6.21,-11.489],[-3.484,-1.786]],"v":[[2.846,0.001],[6.509,-4.879],[43.206,-32.046],[45.583,-77.383],[44.306,-80.702],[40.45,-82.611],[-40.174,-82.611],[-44.029,-80.702],[-45.306,-77.383],[-42.929,-32.046],[-6.232,-4.879],[-2.569,0.001],[-6.232,4.881],[-42.929,32.046],[-45.306,77.383],[-44.029,80.704],[-40.174,82.611],[40.45,82.611],[44.306,80.704],[45.583,77.383],[43.206,32.046],[6.509,4.881]]},"ix":2}},{"ty":"fl","bm":0,"hd":false,"mn":"ADBE Vector Graphic - Fill","nm":"Fill 1","c":{"a":0,"k":[1,1,1,1],"ix":4},"r":1,"o":{"a":0,"k":100,"ix":5}},{"ty":"tr","a":{"a":0,"k":[0,0],"ix":1},"s":{"a":0,"k":[100,100],"ix":3},"sk":{"a":0,"k":0,"ix":4},"p":{"a":0,"k":[51.389,84.672],"ix":2},"r":{"a":0,"k":0,"ix":6},"sa":{"a":0,"k":0,"ix":5},"o":{"a":0,"k":100,"ix":7}}]}],"ind":3,"parent":5},{"ty":0,"nm":"Sand","sr":1,"st":0,"op":268,"ip":0,"hd":false,"ddd":0,"bm":0,"tt":1,"hasMask":false,"ao":0,"ks":{"a":{"a":0,"k":[540,540,0],"ix":1},"s":{"a":0,"k":[100,100,100],"ix":6},"sk":{"a":0,"k":0},"p":{"a":0,"k":[-58,33,0],"ix":2},"r":{"a":0,"k":0,"ix":10},"sa":{"a":0,"k":0},"o":{"a":0,"k":100,"ix":11}},"ef":[],"w":1080,"h":1080,"refId":"comp_1","ind":4,"parent":5},{"ty":4,"nm":"Shape H","sr":1,"st":0,"op":268,"ip":0,"hd":false,"ddd":0,"bm":0,"hasMask":false,"ao":0,"ks":{"a":{"a":0,"k":[51.389,84.834,0],"ix":1},"s":{"a":0,"k":[100,100,100],"ix":6},"sk":{"a":0,"k":0},"p":{"a":1,"k":[{"o":{"x":0.175,"y":0},"i":{"x":0.667,"y":1},"s":[649.389,591.834,0],"t":54,"ti":[0,3.917,0],"to":[0,-3.917,0]},{"o":{"x":0.333,"y":0.333},"i":{"x":0.667,"y":0.667},"s":[649.389,568.334,0],"t":90,"ti":[0,0,0],"to":[0,0,0]},{"o":{"x":0.333,"y":0},"i":{"x":0.667,"y":1},"s":[649.389,568.334,0],"t":106,"ti":[0,-3.917,0],"to":[0,3.917,0]},{"o":{"x":0.167,"y":0.167},"i":{"x":0.833,"y":0.833},"s":[649.389,591.834,0],"t":134,"ti":[0,0,0],"to":[0,0,0]},{"o":{"x":0.175,"y":0},"i":{"x":0.667,"y":1},"s":[649.389,591.834,0],"t":194,"ti":[0,3.917,0],"to":[0,-3.917,0]},{"o":{"x":0.333,"y":0.333},"i":{"x":0.667,"y":0.667},"s":[649.389,568.334,0],"t":230,"ti":[0,0,0],"to":[0,0,0]},{"o":{"x":0.333,"y":0},"i":{"x":0.667,"y":1},"s":[649.389,568.334,0],"t":246,"ti":[0,-3.917,0],"to":[0,3.917,0]},{"s":[649.389,591.834,0],"t":266}],"ix":2},"r":{"a":1,"k":[{"o":{"x":0.631,"y":0},"i":{"x":0.356,"y":1},"s":[0],"t":68},{"o":{"x":0.167,"y":0},"i":{"x":0.356,"y":1},"s":[180],"t":130},{"o":{"x":0.167,"y":0},"i":{"x":0.356,"y":1},"s":[180],"t":208},{"s":[360],"t":262}],"ix":10},"sa":{"a":0,"k":0},"o":{"a":0,"k":100,"ix":11}},"ef":[],"shapes":[{"ty":"gr","bm":0,"hd":false,"mn":"ADBE Vector Group","nm":"Group 4","ix":1,"cix":2,"np":4,"it":[{"ty":"sh","bm":0,"hd":false,"mn":"ADBE Vector Shape - Group","nm":"Path 1","ix":1,"d":1,"ks":{"a":0,"k":{"c":true,"i":[[0,0],[-3.484,1.785],[-6.21,11.49],[3.299,8.571],[0,0],[1.516,0],[0,0],[0.604,-1.05],[0,0],[-10.162,-18.801],[-10.208,-5.231],[0,0],[3.485,-1.786],[6.21,-11.489],[-3.299,-8.569],[0,0],[-1.516,0],[0,0],[-0.605,1.048],[0,0],[10.162,18.801],[10.206,5.23]],"o":[[0,0],[10.206,-5.231],[10.162,-18.801],[0,0],[-0.605,-1.051],[0,0],[-1.516,0],[0,0],[-3.299,8.571],[6.21,11.49],[3.485,1.785],[0,0],[-10.206,5.231],[-10.162,18.801],[0,0],[0.604,1.048],[0,0],[1.516,0],[0,0],[3.299,-8.569],[-6.21,-11.489],[-3.484,-1.786]],"v":[[2.846,0.001],[6.509,-4.879],[43.206,-32.046],[45.583,-77.383],[44.306,-80.702],[40.45,-82.611],[-40.174,-82.611],[-44.029,-80.702],[-45.306,-77.383],[-42.929,-32.046],[-6.232,-4.879],[-2.569,0.001],[-6.232,4.881],[-42.929,32.046],[-45.306,77.383],[-44.029,80.704],[-40.174,82.611],[40.45,82.611],[44.306,80.704],[45.583,77.383],[43.206,32.046],[6.509,4.881]]},"ix":2}},{"ty":"fl","bm":0,"hd":false,"mn":"ADBE Vector Graphic - Fill","nm":"Fill 1","c":{"a":0,"k":[1,1,1,1],"ix":4},"r":1,"o":{"a":0,"k":100,"ix":5}},{"ty":"tr","a":{"a":0,"k":[0,0],"ix":1},"s":{"a":0,"k":[100,100],"ix":3},"sk":{"a":0,"k":0,"ix":4},"p":{"a":0,"k":[51.389,84.672],"ix":2},"r":{"a":0,"k":0,"ix":6},"sa":{"a":0,"k":0,"ix":5},"o":{"a":0,"k":100,"ix":7}}]}],"ind":5}]},{"nm":"","id":"comp_1","layers":[{"ty":4,"nm":"Shape Layer 2","sr":1,"st":122,"op":252,"ip":130,"hd":false,"ddd":0,"bm":0,"hasMask":false,"ao":0,"ks":{"a":{"a":0,"k":[109.25,50,0],"ix":1},"s":{"a":0,"k":[100,100,100],"ix":6},"sk":{"a":0,"k":0},"p":{"a":0,"k":[649.25,599,0],"ix":2},"r":{"a":0,"k":-180,"ix":10},"sa":{"a":0,"k":0},"o":{"a":0,"k":100,"ix":11}},"ef":[],"shapes":[{"ty":"gr","bm":0,"hd":false,"mn":"ADBE Vector Group","nm":"Shape 1","ix":1,"cix":2,"np":3,"it":[{"ty":"sh","bm":0,"hd":false,"mn":"ADBE Vector Shape - Group","nm":"Path 1","ix":1,"d":1,"ks":{"a":0,"k":{"c":false,"i":[[0,0],[0,0]],"o":[[0,0],[0,0]],"v":[[109.25,50],[109.25,122]]},"ix":2}},{"ty":"st","bm":0,"hd":false,"mn":"ADBE Vector Graphic - Stroke","nm":"Stroke 1","lc":1,"lj":1,"ml":4,"o":{"a":0,"k":100,"ix":4},"w":{"a":0,"k":2,"ix":5},"c":{"a":0,"k":[0.76,0.76,0.76,1],"ix":3}},{"ty":"tr","a":{"a":0,"k":[0,0],"ix":1},"s":{"a":0,"k":[100,100],"ix":3},"sk":{"a":0,"k":0,"ix":4},"p":{"a":0,"k":[0,0],"ix":2},"r":{"a":0,"k":0,"ix":6},"sa":{"a":0,"k":0,"ix":5},"o":{"a":0,"k":100,"ix":7}}]},{"ty":"tm","bm":0,"hd":false,"mn":"ADBE Vector Filter - Trim","nm":"Trim Paths 1","ix":2,"e":{"a":1,"k":[{"o":{"x":0.167,"y":0.167},"i":{"x":0.833,"y":0.833},"s":[0],"t":130},{"s":[100],"t":136}],"ix":2},"o":{"a":0,"k":0,"ix":3},"s":{"a":1,"k":[{"o":{"x":0.167,"y":0.167},"i":{"x":0.833,"y":0.833},"s":[0],"t":190},{"s":[52],"t":194}],"ix":1},"m":1}],"ind":1},{"ty":4,"nm":"Shape Layer 1","sr":1,"st":0,"op":130,"ip":8,"hd":false,"ddd":0,"bm":0,"hasMask":false,"ao":0,"ks":{"a":{"a":0,"k":[0,0,0],"ix":1},"s":{"a":0,"k":[100,100,100],"ix":6},"sk":{"a":0,"k":0},"p":{"a":0,"k":[540,540,0],"ix":2},"r":{"a":0,"k":0,"ix":10},"sa":{"a":0,"k":0},"o":{"a":0,"k":100,"ix":11}},"ef":[],"shapes":[{"ty":"gr","bm":0,"hd":false,"mn":"ADBE Vector Group","nm":"Shape 1","ix":1,"cix":2,"np":3,"it":[{"ty":"sh","bm":0,"hd":false,"mn":"ADBE Vector Shape - Group","nm":"Path 1","ix":1,"d":1,"ks":{"a":0,"k":{"c":false,"i":[[0,0],[0,0]],"o":[[0,0],[0,0]],"v":[[109.25,50],[109.25,122]]},"ix":2}},{"ty":"st","bm":0,"hd":false,"mn":"ADBE Vector Graphic - Stroke","nm":"Stroke 1","lc":1,"lj":1,"ml":4,"o":{"a":0,"k":100,"ix":4},"w":{"a":0,"k":2,"ix":5},"c":{"a":0,"k":[0.76,0.76,0.76,1],"ix":3}},{"ty":"tr","a":{"a":0,"k":[0,0],"ix":1},"s":{"a":0,"k":[100,100],"ix":3},"sk":{"a":0,"k":0,"ix":4},"p":{"a":0,"k":[0,0],"ix":2},"r":{"a":0,"k":0,"ix":6},"sa":{"a":0,"k":0,"ix":5},"o":{"a":0,"k":100,"ix":7}}]},{"ty":"tm","bm":0,"hd":false,"mn":"ADBE Vector Filter - Trim","nm":"Trim Paths 1","ix":2,"e":{"a":1,"k":[{"o":{"x":0.167,"y":0.167},"i":{"x":0.833,"y":0.833},"s":[0],"t":8},{"s":[100],"t":14}],"ix":2},"o":{"a":0,"k":0,"ix":3},"s":{"a":1,"k":[{"o":{"x":0.167,"y":0.167},"i":{"x":0.833,"y":0.833},"s":[0],"t":68},{"s":[52],"t":72}],"ix":1},"m":1}],"ind":2},{"ty":0,"nm":"Pre-comp 1","sr":1,"st":130,"op":268,"ip":130,"hd":false,"ddd":0,"bm":0,"hasMask":false,"ao":0,"ks":{"a":{"a":0,"k":[73.5,122.5,0],"ix":1},"s":{"a":0,"k":[100,100,100],"ix":6},"sk":{"a":0,"k":0},"p":{"a":0,"k":[650.5,559.25,0],"ix":2},"r":{"a":0,"k":180,"ix":10},"sa":{"a":0,"k":0},"o":{"a":0,"k":100,"ix":11}},"ef":[],"w":147,"h":245,"refId":"comp_2","ind":3},{"ty":4,"nm":"Sand Up Mask","sr":1,"st":0,"op":130,"ip":0,"hd":false,"ddd":0,"bm":0,"hasMask":false,"td":1,"ao":0,"ks":{"a":{"a":0,"k":[116,-18.75,0],"ix":1},"s":{"a":0,"k":[100,173.267,100],"ix":6},"sk":{"a":0,"k":0},"p":{"a":0,"k":[651.5,548.75,0],"ix":2},"r":{"a":0,"k":0,"ix":10},"sa":{"a":0,"k":0},"o":{"a":0,"k":100,"ix":11}},"ef":[],"shapes":[{"ty":"gr","bm":0,"hd":false,"mn":"ADBE Vector Group","nm":"Rectangle 1","ix":1,"cix":2,"np":3,"it":[{"ty":"rc","bm":0,"hd":false,"mn":"ADBE Vector Shape - Rect","nm":"Rectangle Path 1","d":1,"p":{"a":0,"k":[0,0],"ix":3},"r":{"a":0,"k":0,"ix":4},"s":{"a":0,"k":[154,50.5],"ix":2}},{"ty":"fl","bm":0,"hd":false,"mn":"ADBE Vector Graphic - Fill","nm":"Fill 1","c":{"a":0,"k":[0.76,0.76,0.76,1],"ix":4},"r":1,"o":{"a":0,"k":100,"ix":5}},{"ty":"tr","a":{"a":0,"k":[0,0],"ix":1},"s":{"a":0,"k":[100,100],"ix":3},"sk":{"a":0,"k":0,"ix":4},"p":{"a":0,"k":[116,-18.75],"ix":2},"r":{"a":0,"k":0,"ix":6},"sa":{"a":0,"k":0,"ix":5},"o":{"a":0,"k":100,"ix":7}}]}],"ind":4},{"ty":4,"nm":"Sand Up","sr":1,"st":0,"op":130,"ip":0,"hd":false,"ddd":0,"bm":0,"tt":1,"hasMask":false,"ao":0,"ks":{"a":{"a":0,"k":[539.503,644.926,0],"ix":1},"s":{"a":0,"k":[28.384,28.384,100],"ix":6},"sk":{"a":0,"k":0},"p":{"a":1,"k":[{"o":{"x":0.167,"y":0.167},"i":{"x":0.833,"y":0.833},"s":[649.634,526.446,0],"t":0,"ti":[0,-14.917,0],"to":[0,14.917,0]},{"s":[649.634,615.946,0],"t":110}],"ix":2},"r":{"a":0,"k":180,"ix":10},"sa":{"a":0,"k":0},"o":{"a":0,"k":100,"ix":11}},"ef":[],"shapes":[{"ty":"gr","bm":0,"hd":false,"mn":"ADBE Vector Group","nm":"Group 1","ix":1,"cix":2,"np":2,"it":[{"ty":"sh","bm":0,"hd":false,"mn":"ADBE Vector Shape - Group","nm":"Path 1","ix":1,"d":1,"ks":{"a":1,"k":[{"o":{"x":0.167,"y":0.167},"i":{"x":0.833,"y":0.833},"s":[{"c":true,"i":[[30.153,54.394],[10.015,8.773],[22.16,0],[23.963,-10.917],[38.978,-9.448],[-8.501,-22.082],[0,0],[-5.275,0],[0,0],[0,0],[0,0],[0,0],[-2.104,3.648],[0,0]],"o":[[-28.32,-8.08],[-14.127,-12.382],[-19.058,0],[-13.118,5.976],[-35.959,65.582],[0,0],[2.104,3.648],[0,0],[0,0],[0,0],[0,0],[5.27,0],[0,0],[8.626,-22.406]],"v":[[155.057,-10.17],[85.261,-48.982],[-0.16,-105.688],[-69.059,-43.543],[-152.276,-19.597],[-199.97,145.63],[-186.72,164.229],[-173.308,170.865],[-45.221,163.819],[8.642,163.819],[76.699,163.819],[176.715,171.746],[194.53,160.706],[213.945,140.345]]}],"t":0},{"o":{"x":0.167,"y":0.167},"i":{"x":0.833,"y":0.833},"s":[{"c":true,"i":[[30.153,54.394],[10.015,8.773],[22.16,0],[23.963,-10.917],[38.978,-9.448],[-8.501,-22.082],[0,0],[-5.275,0],[-43.292,10.679],[-17.561,-0.652],[-23.486,-6.826],[0,0],[-2.104,3.648],[0,0]],"o":[[-28.32,-8.08],[-14.127,-12.382],[-19.058,0],[-13.118,5.976],[-35.959,65.582],[0,0],[2.104,3.648],[0,0],[21.022,-5.186],[21.461,0.797],[35.31,10.262],[5.27,0],[0,0],[8.626,-22.406]],"v":[[155.057,-10.17],[85.261,-48.982],[-0.16,-105.688],[-69.059,-43.543],[-152.276,-19.597],[-193.805,148.272],[-199.932,169.513],[-140.72,163.819],[-54.509,149.084],[2.957,132.992],[69.497,152.702],[139.723,163.819],[205.1,171.275],[257.103,127.134]]}],"t":32},{"s":[{"c":true,"i":[[30.153,54.394],[10.015,8.773],[22.16,0],[23.963,-10.917],[38.978,-9.448],[-8.501,-22.082],[0,0],[-35.119,3.657],[-43.822,20.153],[-17.561,-0.652],[-20.841,-12.8],[0,0],[-2.104,3.648],[0,0]],"o":[[-28.32,-8.08],[-14.127,-12.382],[-19.058,0],[-13.118,5.976],[-35.959,65.582],[0,0],[2.104,3.648],[0,0],[19.671,-9.047],[21.461,0.797],[31.225,19.178],[5.27,0],[0,0],[8.626,-22.406]],"v":[[155.057,-10.17],[85.261,-48.982],[-0.16,-105.688],[-69.059,-43.543],[-152.276,-19.597],[-202.612,144.749],[-194.647,162.467],[-140.72,163.819],[-72.125,138.515],[-1.447,91.596],[77.424,136.849],[140.604,165.58],[202.457,161.587],[222.753,134.18]]}],"t":56}],"ix":2}},{"ty":"fl","bm":0,"hd":false,"mn":"ADBE Vector Graphic - Fill","nm":"Fill 1","c":{"a":0,"k":[0.76,0.76,0.76,1],"ix":4},"r":1,"o":{"a":0,"k":100,"ix":5}},{"ty":"tr","a":{"a":0,"k":[0,0],"ix":1},"s":{"a":0,"k":[100,100],"ix":3},"sk":{"a":0,"k":0,"ix":4},"p":{"a":0,"k":[539.662,539.238],"ix":2},"r":{"a":0,"k":0,"ix":6},"sa":{"a":0,"k":0,"ix":5},"o":{"a":0,"k":100,"ix":7}}]}],"ind":5},{"ty":4,"nm":"Sand Down","sr":1,"st":0,"op":130,"ip":0,"hd":false,"ddd":0,"bm":0,"hasMask":false,"ao":0,"ks":{"a":{"a":0,"k":[539.503,644.926,0],"ix":1},"s":{"a":0,"k":[28.384,28.384,100],"ix":6},"sk":{"a":0,"k":0},"p":{"a":1,"k":[{"o":{"x":0.167,"y":0.167},"i":{"x":0.833,"y":0.833},"s":[649.634,727.946,0],"t":0,"ti":[0,11.667,0],"to":[0,-11.667,0]},{"s":[649.634,657.946,0],"t":70}],"ix":2},"r":{"a":0,"k":0,"ix":10},"sa":{"a":0,"k":0},"o":{"a":0,"k":100,"ix":11}},"ef":[],"shapes":[{"ty":"gr","bm":0,"hd":false,"mn":"ADBE Vector Group","nm":"Group 1","ix":1,"cix":2,"np":2,"it":[{"ty":"sh","bm":0,"hd":false,"mn":"ADBE Vector Shape - Group","nm":"Path 1","ix":1,"d":1,"ks":{"a":0,"k":{"c":true,"i":[[30.153,54.394],[10.015,8.773],[22.16,0],[23.963,-10.917],[38.978,-9.448],[-8.501,-22.082],[0,0],[-5.275,0],[0,0],[-2.104,3.648],[0,0]],"o":[[-28.32,-8.08],[-14.127,-12.382],[-19.058,0],[-13.118,5.976],[-35.959,65.582],[0,0],[2.104,3.648],[0,0],[5.27,0],[0,0],[8.626,-22.406]],"v":[[155.057,-10.17],[85.261,-48.982],[-0.16,-105.688],[-69.059,-43.543],[-152.276,-19.597],[-158.574,145.63],[-154.132,157.183],[-140.72,163.819],[139.723,163.819],[153.134,157.183],[157.576,145.63]]},"ix":2}},{"ty":"fl","bm":0,"hd":false,"mn":"ADBE Vector Graphic - Fill","nm":"Fill 1","c":{"a":0,"k":[0.76,0.76,0.76,1],"ix":4},"r":1,"o":{"a":0,"k":100,"ix":5}},{"ty":"tr","a":{"a":0,"k":[0,0],"ix":1},"s":{"a":0,"k":[100,100],"ix":3},"sk":{"a":0,"k":0,"ix":4},"p":{"a":0,"k":[539.662,539.238],"ix":2},"r":{"a":0,"k":0,"ix":6},"sa":{"a":0,"k":0,"ix":5},"o":{"a":0,"k":100,"ix":7}}]}],"ind":6}]},{"nm":"","id":"comp_2","layers":[{"ty":4,"nm":"Sand Up Mask 2","sr":1,"st":0,"op":138,"ip":0,"hd":false,"ddd":0,"bm":0,"hasMask":false,"td":1,"ao":0,"ks":{"a":{"a":0,"k":[116,-18.75,0],"ix":1},"s":{"a":0,"k":[100,173.267,100],"ix":6},"sk":{"a":0,"k":0},"p":{"a":0,"k":[77.5,46.75,0],"ix":2},"r":{"a":0,"k":0,"ix":10},"sa":{"a":0,"k":0},"o":{"a":0,"k":100,"ix":11}},"ef":[],"shapes":[{"ty":"gr","bm":0,"hd":false,"mn":"ADBE Vector Group","nm":"Rectangle 1","ix":1,"cix":2,"np":3,"it":[{"ty":"rc","bm":0,"hd":false,"mn":"ADBE Vector Shape - Rect","nm":"Rectangle Path 1","d":1,"p":{"a":0,"k":[0,0],"ix":3},"r":{"a":0,"k":0,"ix":4},"s":{"a":0,"k":[154,50.5],"ix":2}},{"ty":"fl","bm":0,"hd":false,"mn":"ADBE Vector Graphic - Fill","nm":"Fill 1","c":{"a":0,"k":[0.76,0.76,0.76,1],"ix":4},"r":1,"o":{"a":0,"k":100,"ix":5}},{"ty":"tr","a":{"a":0,"k":[0,0],"ix":1},"s":{"a":0,"k":[100,100],"ix":3},"sk":{"a":0,"k":0,"ix":4},"p":{"a":0,"k":[116,-18.75],"ix":2},"r":{"a":0,"k":0,"ix":6},"sa":{"a":0,"k":0,"ix":5},"o":{"a":0,"k":100,"ix":7}}]}],"ind":1},{"ty":4,"nm":"Sand Up 2","sr":1,"st":0,"op":138,"ip":0,"hd":false,"ddd":0,"bm":0,"tt":1,"hasMask":false,"ao":0,"ks":{"a":{"a":0,"k":[539.503,644.926,0],"ix":1},"s":{"a":0,"k":[28.384,28.384,100],"ix":6},"sk":{"a":0,"k":0},"p":{"a":1,"k":[{"o":{"x":0.167,"y":0.167},"i":{"x":0.833,"y":0.833},"s":[75.634,24.446,0],"t":0,"ti":[0,-14.917,0],"to":[0,14.917,0]},{"s":[75.634,113.946,0],"t":110}],"ix":2},"r":{"a":0,"k":180,"ix":10},"sa":{"a":0,"k":0},"o":{"a":0,"k":100,"ix":11}},"ef":[],"shapes":[{"ty":"gr","bm":0,"hd":false,"mn":"ADBE Vector Group","nm":"Group 1","ix":1,"cix":2,"np":2,"it":[{"ty":"sh","bm":0,"hd":false,"mn":"ADBE Vector Shape - Group","nm":"Path 1","ix":1,"d":1,"ks":{"a":1,"k":[{"o":{"x":0.167,"y":0.167},"i":{"x":0.833,"y":0.833},"s":[{"c":true,"i":[[30.153,54.394],[10.015,8.773],[22.16,0],[23.963,-10.917],[38.978,-9.448],[-8.501,-22.082],[0,0],[-5.275,0],[0,0],[0,0],[0,0],[0,0],[-2.104,3.648],[0,0]],"o":[[-28.32,-8.08],[-14.127,-12.382],[-19.058,0],[-13.118,5.976],[-35.959,65.582],[0,0],[2.104,3.648],[0,0],[0,0],[0,0],[0,0],[5.27,0],[0,0],[8.626,-22.406]],"v":[[155.057,-10.17],[85.261,-48.982],[-0.16,-105.688],[-69.059,-43.543],[-152.276,-19.597],[-199.97,145.63],[-186.72,164.229],[-173.308,170.865],[-45.221,163.819],[8.642,163.819],[76.699,163.819],[176.715,171.746],[194.53,160.706],[213.945,140.345]]}],"t":0},{"o":{"x":0.167,"y":0.167},"i":{"x":0.833,"y":0.833},"s":[{"c":true,"i":[[30.153,54.394],[10.015,8.773],[22.16,0],[23.963,-10.917],[38.978,-9.448],[-8.501,-22.082],[0,0],[-5.275,0],[-43.292,10.679],[-17.561,-0.652],[-23.486,-6.826],[0,0],[-2.104,3.648],[0,0]],"o":[[-28.32,-8.08],[-14.127,-12.382],[-19.058,0],[-13.118,5.976],[-35.959,65.582],[0,0],[2.104,3.648],[0,0],[21.022,-5.186],[21.461,0.797],[35.31,10.262],[5.27,0],[0,0],[8.626,-22.406]],"v":[[155.057,-10.17],[85.261,-48.982],[-0.16,-105.688],[-69.059,-43.543],[-152.276,-19.597],[-193.805,148.272],[-199.932,169.513],[-140.72,163.819],[-54.509,149.084],[2.957,132.992],[69.497,152.702],[139.723,163.819],[205.1,171.275],[257.103,127.134]]}],"t":32},{"s":[{"c":true,"i":[[30.153,54.394],[10.015,8.773],[22.16,0],[23.963,-10.917],[38.978,-9.448],[-8.501,-22.082],[0,0],[-35.119,3.657],[-43.822,20.153],[-17.561,-0.652],[-20.841,-12.8],[0,0],[-2.104,3.648],[0,0]],"o":[[-28.32,-8.08],[-14.127,-12.382],[-19.058,0],[-13.118,5.976],[-35.959,65.582],[0,0],[2.104,3.648],[0,0],[19.671,-9.047],[21.461,0.797],[31.225,19.178],[5.27,0],[0,0],[8.626,-22.406]],"v":[[155.057,-10.17],[85.261,-48.982],[-0.16,-105.688],[-69.059,-43.543],[-152.276,-19.597],[-202.612,144.749],[-194.647,162.467],[-140.72,163.819],[-72.125,138.515],[-1.447,91.596],[77.424,136.849],[140.604,165.58],[202.457,161.587],[222.753,134.18]]}],"t":56}],"ix":2}},{"ty":"fl","bm":0,"hd":false,"mn":"ADBE Vector Graphic - Fill","nm":"Fill 1","c":{"a":0,"k":[0.76,0.76,0.76,1],"ix":4},"r":1,"o":{"a":0,"k":100,"ix":5}},{"ty":"tr","a":{"a":0,"k":[0,0],"ix":1},"s":{"a":0,"k":[100,100],"ix":3},"sk":{"a":0,"k":0,"ix":4},"p":{"a":0,"k":[539.662,539.238],"ix":2},"r":{"a":0,"k":0,"ix":6},"sa":{"a":0,"k":0,"ix":5},"o":{"a":0,"k":100,"ix":7}}]}],"ind":2},{"ty":4,"nm":"Sand Down 2","sr":1,"st":0,"op":138,"ip":0,"hd":false,"ddd":0,"bm":0,"hasMask":false,"ao":0,"ks":{"a":{"a":0,"k":[539.503,644.926,0],"ix":1},"s":{"a":0,"k":[28.384,28.384,100],"ix":6},"sk":{"a":0,"k":0},"p":{"a":1,"k":[{"o":{"x":0.167,"y":0.167},"i":{"x":0.833,"y":0.833},"s":[75.634,225.946,0],"t":0,"ti":[0,11.667,0],"to":[0,-11.667,0]},{"s":[75.634,155.946,0],"t":70}],"ix":2},"r":{"a":0,"k":0,"ix":10},"sa":{"a":0,"k":0},"o":{"a":0,"k":100,"ix":11}},"ef":[],"shapes":[{"ty":"gr","bm":0,"hd":false,"mn":"ADBE Vector Group","nm":"Group 1","ix":1,"cix":2,"np":2,"it":[{"ty":"sh","bm":0,"hd":false,"mn":"ADBE Vector Shape - Group","nm":"Path 1","ix":1,"d":1,"ks":{"a":0,"k":{"c":true,"i":[[30.153,54.394],[10.015,8.773],[22.16,0],[23.963,-10.917],[38.978,-9.448],[-8.501,-22.082],[0,0],[-5.275,0],[0,0],[-2.104,3.648],[0,0]],"o":[[-28.32,-8.08],[-14.127,-12.382],[-19.058,0],[-13.118,5.976],[-35.959,65.582],[0,0],[2.104,3.648],[0,0],[5.27,0],[0,0],[8.626,-22.406]],"v":[[155.057,-10.17],[85.261,-48.982],[-0.16,-105.688],[-69.059,-43.543],[-152.276,-19.597],[-158.574,145.63],[-154.132,157.183],[-140.72,163.819],[139.723,163.819],[153.134,157.183],[157.576,145.63]]},"ix":2}},{"ty":"fl","bm":0,"hd":false,"mn":"ADBE Vector Graphic - Fill","nm":"Fill 1","c":{"a":0,"k":[0.76,0.76,0.76,1],"ix":4},"r":1,"o":{"a":0,"k":100,"ix":5}},{"ty":"tr","a":{"a":0,"k":[0,0],"ix":1},"s":{"a":0,"k":[100,100],"ix":3},"sk":{"a":0,"k":0,"ix":4},"p":{"a":0,"k":[539.662,539.238],"ix":2},"r":{"a":0,"k":0,"ix":6},"sa":{"a":0,"k":0,"ix":5},"o":{"a":0,"k":100,"ix":7}}]}],"ind":3}]}]}